[
    {
        "Gacha根ID": 10001,
        "道具ID": 1016,
        "类型": 11,
        "概率权重": 100,
        "闪卡概率": 0
    },
    {
        "Gacha根ID": 10001,
        "道具ID": 1003,
        "类型": 11,
        "概率权重": 100,
        "闪卡概率": 0
    },
    {
        "Gacha根ID": 10001,
        "道具ID": 1022,
        "类型": 11,
        "概率权重": "",
        "闪卡概率": 0
    },
    {
        "Gacha根ID": 10001,
        "道具ID": 1030,
        "类型": 11,
        "概率权重": "",
        "闪卡概率": 0
    },
    {
        "Gacha根ID": 10001,
        "道具ID": 1026,
        "类型": 11,
        "概率权重": "",
        "闪卡概率": 0
    },
    {
        "Gacha根ID": 10001,
        "道具ID": 1029,
        "类型": 11,
        "概率权重": "",
        "闪卡概率": 0
    },
    {
        "Gacha根ID": 10001,
        "道具ID": 1006,
        "类型": 12,
        "概率权重": 100,
        "闪卡概率": 0
    },
    {
        "Gacha根ID": 10001,
        "道具ID": 1014,
        "类型": 12,
        "概率权重": 100,
        "闪卡概率": 0
    },
    {
        "Gacha根ID": 10001,
        "道具ID": 1015,
        "类型": 12,
        "概率权重": 100,
        "闪卡概率": 0
    },
    {
        "Gacha根ID": 10001,
        "道具ID": 1020,
        "类型": 12,
        "概率权重": 100,
        "闪卡概率": 0
    },
    {
        "Gacha根ID": 10001,
        "道具ID": 1021,
        "类型": 12,
        "概率权重": 100,
        "闪卡概率": 0
    },
    {
        "Gacha根ID": 10001,
        "道具ID": 1023,
        "类型": 12,
        "概率权重": 100,
        "闪卡概率": 0
    },
    {
        "Gacha根ID": 10001,
        "道具ID": 1024,
        "类型": 12,
        "概率权重": 100,
        "闪卡概率": 0
    },
    {
        "Gacha根ID": 10001,
        "道具ID": 1025,
        "类型": 12,
        "概率权重": 100,
        "闪卡概率": 0
    },
    {
        "Gacha根ID": 10001,
        "道具ID": 1027,
        "类型": 12,
        "概率权重": 100,
        "闪卡概率": 0
    },
    {
        "Gacha根ID": 10001,
        "道具ID": 1031,
        "类型": 12,
        "概率权重": 100,
        "闪卡概率": 0
    },
    {
        "Gacha根ID": 10001,
        "道具ID": 1032,
        "类型": 12,
        "概率权重": 100,
        "闪卡概率": 0
    },
    {
        "Gacha根ID": 10001,
        "道具ID": 1034,
        "类型": 12,
        "概率权重": 100,
        "闪卡概率": 0
    },
    {
        "Gacha根ID": 10001,
        "道具ID": 11501,
        "类型": 21,
        "概率权重": 100,
        "闪卡概率": 0
    },
    {
        "Gacha根ID": 10001,
        "道具ID": 11502,
        "类型": 21,
        "概率权重": 100,
        "闪卡概率": 0
    },
    {
        "Gacha根ID": 10001,
        "道具ID": 12501,
        "类型": 21,
        "概率权重": 100,
        "闪卡概率": 0
    },
    {
        "Gacha根ID": 10001,
        "道具ID": 12502,
        "类型": 21,
        "概率权重": 100,
        "闪卡概率": 0
    },
    {
        "Gacha根ID": 10001,
        "道具ID": 13504,
        "类型": 21,
        "概率权重": 100,
        "闪卡概率": 0
    },
    {
        "Gacha根ID": 10001,
        "道具ID": 13505,
        "类型": 21,
        "概率权重": 100,
        "闪卡概率": 0
    },
    {
        "Gacha根ID": 10001,
        "道具ID": 14501,
        "类型": 21,
        "概率权重": 100,
        "闪卡概率": 0
    },
    {
        "Gacha根ID": 10001,
        "道具ID": 14502,
        "类型": 21,
        "概率权重": 100,
        "闪卡概率": 0
    },
    {
        "Gacha根ID": 10001,
        "道具ID": 15501,
        "类型": 21,
        "概率权重": 100,
        "闪卡概率": 0
    },
    {
        "Gacha根ID": 10001,
        "道具ID": 15502,
        "类型": 21,
        "概率权重": 100,
        "闪卡概率": 0
    },
    {
        "Gacha根ID": 10001,
        "道具ID": 11401,
        "类型": 22,
        "概率权重": 100,
        "闪卡概率": 0
    },
    {
        "Gacha根ID": 10001,
        "道具ID": 11402,
        "类型": 22,
        "概率权重": 100,
        "闪卡概率": 0
    },
    {
        "Gacha根ID": 10001,
        "道具ID": 11404,
        "类型": 22,
        "概率权重": 100,
        "闪卡概率": 0
    },
    {
        "Gacha根ID": 10001,
        "道具ID": 11407,
        "类型": 22,
        "概率权重": 100,
        "闪卡概率": 0
    },
    {
        "Gacha根ID": 10001,
        "道具ID": 12401,
        "类型": 22,
        "概率权重": 100,
        "闪卡概率": 0
    },
    {
        "Gacha根ID": 10001,
        "道具ID": 12402,
        "类型": 22,
        "概率权重": 100,
        "闪卡概率": 0
    },
    {
        "Gacha根ID": 10001,
        "道具ID": 12404,
        "类型": 22,
        "概率权重": 100,
        "闪卡概率": 0
    },
    {
        "Gacha根ID": 10001,
        "道具ID": 12406,
        "类型": 22,
        "概率权重": 100,
        "闪卡概率": 0
    },
    {
        "Gacha根ID": 10001,
        "道具ID": 13401,
        "类型": 22,
        "概率权重": 100,
        "闪卡概率": 0
    },
    {
        "Gacha根ID": 10001,
        "道具ID": 13404,
        "类型": 22,
        "概率权重": 100,
        "闪卡概率": 0
    },
    {
        "Gacha根ID": 10001,
        "道具ID": 14401,
        "类型": 22,
        "概率权重": 100,
        "闪卡概率": 0
    },
    {
        "Gacha根ID": 10001,
        "道具ID": 14402,
        "类型": 22,
        "概率权重": 100,
        "闪卡概率": 0
    },
    {
        "Gacha根ID": 10001,
        "道具ID": 14403,
        "类型": 22,
        "概率权重": 100,
        "闪卡概率": 0
    },
    {
        "Gacha根ID": 10001,
        "道具ID": 14404,
        "类型": 22,
        "概率权重": 100,
        "闪卡概率": 0
    },
    {
        "Gacha根ID": 10001,
        "道具ID": 15401,
        "类型": 22,
        "概率权重": 100,
        "闪卡概率": 0
    },
    {
        "Gacha根ID": 10001,
        "道具ID": 15402,
        "类型": 22,
        "概率权重": 100,
        "闪卡概率": 0
    },
    {
        "Gacha根ID": 10001,
        "道具ID": 15403,
        "类型": 22,
        "概率权重": 100,
        "闪卡概率": 0
    },
    {
        "Gacha根ID": 10001,
        "道具ID": 15404,
        "类型": 22,
        "概率权重": 100,
        "闪卡概率": 0
    },
    {
        "Gacha根ID": 10001,
        "道具ID": 11405,
        "类型": 22,
        "概率权重": 100,
        "闪卡概率": 0
    },
    {
        "Gacha根ID": 10001,
        "道具ID": 12405,
        "类型": 22,
        "概率权重": 100,
        "闪卡概率": 0
    },
    {
        "Gacha根ID": 10001,
        "道具ID": 14407,
        "类型": 22,
        "概率权重": 100,
        "闪卡概率": 0
    },
    {
        "Gacha根ID": 10001,
        "道具ID": 14408,
        "类型": 22,
        "概率权重": 100,
        "闪卡概率": 0
    },
    {
        "Gacha根ID": 10001,
        "道具ID": 15405,
        "类型": 22,
        "概率权重": 100,
        "闪卡概率": 0
    },
    {
        "Gacha根ID": 10001,
        "道具ID": 11301,
        "类型": 23,
        "概率权重": 100,
        "闪卡概率": 0
    },
    {
        "Gacha根ID": 10001,
        "道具ID": 11302,
        "类型": 23,
        "概率权重": 100,
        "闪卡概率": 0
    },
    {
        "Gacha根ID": 10001,
        "道具ID": 11306,
        "类型": 23,
        "概率权重": 100,
        "闪卡概率": 0
    },
    {
        "Gacha根ID": 10001,
        "道具ID": 12301,
        "类型": 23,
        "概率权重": 100,
        "闪卡概率": 0
    },
    {
        "Gacha根ID": 10001,
        "道具ID": 12302,
        "类型": 23,
        "概率权重": 100,
        "闪卡概率": 0
    },
    {
        "Gacha根ID": 10001,
        "道具ID": 12305,
        "类型": 23,
        "概率权重": 100,
        "闪卡概率": 0
    },
    {
        "Gacha根ID": 10001,
        "道具ID": 13303,
        "类型": 23,
        "概率权重": 100,
        "闪卡概率": 0
    },
    {
        "Gacha根ID": 10001,
        "道具ID": 14301,
        "类型": 23,
        "概率权重": 100,
        "闪卡概率": 0
    },
    {
        "Gacha根ID": 10001,
        "道具ID": 14302,
        "类型": 23,
        "概率权重": 100,
        "闪卡概率": 0
    },
    {
        "Gacha根ID": 10001,
        "道具ID": 14304,
        "类型": 23,
        "概率权重": 100,
        "闪卡概率": 0
    },
    {
        "Gacha根ID": 10001,
        "道具ID": 15301,
        "类型": 23,
        "概率权重": 100,
        "闪卡概率": 0
    },
    {
        "Gacha根ID": 10001,
        "道具ID": 15302,
        "类型": 23,
        "概率权重": 100,
        "闪卡概率": 0
    },
    {
        "Gacha根ID": 10001,
        "道具ID": 15304,
        "类型": 23,
        "概率权重": 100,
        "闪卡概率": 0
    },
    {
        "Gacha根ID": 10001,
        "道具ID": 11304,
        "类型": 23,
        "概率权重": 100,
        "闪卡概率": 0
    },
    {
        "Gacha根ID": 10001,
        "道具ID": 12304,
        "类型": 23,
        "概率权重": 100,
        "闪卡概率": 0
    },
    {
        "Gacha根ID": 10001,
        "道具ID": 14306,
        "类型": 23,
        "概率权重": 100,
        "闪卡概率": 0
    },
    {
        "Gacha根ID": 10001,
        "道具ID": 15306,
        "类型": 23,
        "概率权重": 100,
        "闪卡概率": 0
    },
    {
        "Gacha根ID": 10002,
        "道具ID": 1016,
        "类型": 11,
        "概率权重": 100,
        "闪卡概率": 0
    },
    {
        "Gacha根ID": 10002,
        "道具ID": 1003,
        "类型": 11,
        "概率权重": 100,
        "闪卡概率": 0
    },
    {
        "Gacha根ID": 10002,
        "道具ID": 1022,
        "类型": 11,
        "概率权重": "",
        "闪卡概率": 0
    },
    {
        "Gacha根ID": 10002,
        "道具ID": 1030,
        "类型": 11,
        "概率权重": "",
        "闪卡概率": 0
    },
    {
        "Gacha根ID": 10002,
        "道具ID": 1026,
        "类型": 11,
        "概率权重": "",
        "闪卡概率": 0
    },
    {
        "Gacha根ID": 10002,
        "道具ID": 1029,
        "类型": 11,
        "概率权重": "",
        "闪卡概率": 0
    },
    {
        "Gacha根ID": 10002,
        "道具ID": 1006,
        "类型": 12,
        "概率权重": 100,
        "闪卡概率": 0
    },
    {
        "Gacha根ID": 10002,
        "道具ID": 1014,
        "类型": 12,
        "概率权重": 100,
        "闪卡概率": 0
    },
    {
        "Gacha根ID": 10002,
        "道具ID": 1015,
        "类型": 12,
        "概率权重": 100,
        "闪卡概率": 0
    },
    {
        "Gacha根ID": 10002,
        "道具ID": 1020,
        "类型": 12,
        "概率权重": 100,
        "闪卡概率": 0
    },
    {
        "Gacha根ID": 10002,
        "道具ID": 1021,
        "类型": 12,
        "概率权重": 100,
        "闪卡概率": 0
    },
    {
        "Gacha根ID": 10002,
        "道具ID": 1023,
        "类型": 12,
        "概率权重": 100,
        "闪卡概率": 0
    },
    {
        "Gacha根ID": 10002,
        "道具ID": 1024,
        "类型": 12,
        "概率权重": 100,
        "闪卡概率": 0
    },
    {
        "Gacha根ID": 10002,
        "道具ID": 1025,
        "类型": 12,
        "概率权重": 100,
        "闪卡概率": 0
    },
    {
        "Gacha根ID": 10002,
        "道具ID": 1027,
        "类型": 12,
        "概率权重": 100,
        "闪卡概率": 0
    },
    {
        "Gacha根ID": 10002,
        "道具ID": 1031,
        "类型": 12,
        "概率权重": "",
        "闪卡概率": 0
    },
    {
        "Gacha根ID": 10002,
        "道具ID": 1032,
        "类型": 12,
        "概率权重": 100,
        "闪卡概率": 0
    },
    {
        "Gacha根ID": 10002,
        "道具ID": 1034,
        "类型": 12,
        "概率权重": 100,
        "闪卡概率": 0
    },
    {
        "Gacha根ID": 10002,
        "道具ID": 11501,
        "类型": 21,
        "概率权重": 100,
        "闪卡概率": 0
    },
    {
        "Gacha根ID": 10002,
        "道具ID": 11502,
        "类型": 21,
        "概率权重": 100,
        "闪卡概率": 0
    },
    {
        "Gacha根ID": 10002,
        "道具ID": 12501,
        "类型": 21,
        "概率权重": 100,
        "闪卡概率": 0
    },
    {
        "Gacha根ID": 10002,
        "道具ID": 12502,
        "类型": 21,
        "概率权重": 100,
        "闪卡概率": 0
    },
    {
        "Gacha根ID": 10002,
        "道具ID": 13504,
        "类型": 21,
        "概率权重": 100,
        "闪卡概率": 0
    },
    {
        "Gacha根ID": 10002,
        "道具ID": 13505,
        "类型": 21,
        "概率权重": 100,
        "闪卡概率": 0
    },
    {
        "Gacha根ID": 10002,
        "道具ID": 14501,
        "类型": 21,
        "概率权重": 100,
        "闪卡概率": 0
    },
    {
        "Gacha根ID": 10002,
        "道具ID": 14502,
        "类型": 21,
        "概率权重": 100,
        "闪卡概率": 0
    },
    {
        "Gacha根ID": 10002,
        "道具ID": 15501,
        "类型": 21,
        "概率权重": 100,
        "闪卡概率": 0
    },
    {
        "Gacha根ID": 10002,
        "道具ID": 15502,
        "类型": 21,
        "概率权重": 100,
        "闪卡概率": 0
    },
    {
        "Gacha根ID": 10002,
        "道具ID": 11401,
        "类型": 22,
        "概率权重": 100,
        "闪卡概率": 0
    },
    {
        "Gacha根ID": 10002,
        "道具ID": 11402,
        "类型": 22,
        "概率权重": 100,
        "闪卡概率": 0
    },
    {
        "Gacha根ID": 10002,
        "道具ID": 11404,
        "类型": 22,
        "概率权重": 100,
        "闪卡概率": 0
    },
    {
        "Gacha根ID": 10002,
        "道具ID": 11407,
        "类型": 22,
        "概率权重": 100,
        "闪卡概率": 0
    },
    {
        "Gacha根ID": 10002,
        "道具ID": 12401,
        "类型": 22,
        "概率权重": 100,
        "闪卡概率": 0
    },
    {
        "Gacha根ID": 10002,
        "道具ID": 12402,
        "类型": 22,
        "概率权重": 100,
        "闪卡概率": 0
    },
    {
        "Gacha根ID": 10002,
        "道具ID": 12404,
        "类型": 22,
        "概率权重": 100,
        "闪卡概率": 0
    },
    {
        "Gacha根ID": 10002,
        "道具ID": 12406,
        "类型": 22,
        "概率权重": 100,
        "闪卡概率": 0
    },
    {
        "Gacha根ID": 10002,
        "道具ID": 13401,
        "类型": 22,
        "概率权重": 100,
        "闪卡概率": 0
    },
    {
        "Gacha根ID": 10002,
        "道具ID": 13404,
        "类型": 22,
        "概率权重": 100,
        "闪卡概率": 0
    },
    {
        "Gacha根ID": 10002,
        "道具ID": 14401,
        "类型": 22,
        "概率权重": 100,
        "闪卡概率": 0
    },
    {
        "Gacha根ID": 10002,
        "道具ID": 14402,
        "类型": 22,
        "概率权重": 100,
        "闪卡概率": 0
    },
    {
        "Gacha根ID": 10002,
        "道具ID": 14403,
        "类型": 22,
        "概率权重": 100,
        "闪卡概率": 0
    },
    {
        "Gacha根ID": 10002,
        "道具ID": 14404,
        "类型": 22,
        "概率权重": 100,
        "闪卡概率": 0
    },
    {
        "Gacha根ID": 10002,
        "道具ID": 15401,
        "类型": 22,
        "概率权重": 100,
        "闪卡概率": 0
    },
    {
        "Gacha根ID": 10002,
        "道具ID": 15402,
        "类型": 22,
        "概率权重": 100,
        "闪卡概率": 0
    },
    {
        "Gacha根ID": 10002,
        "道具ID": 15403,
        "类型": 22,
        "概率权重": 100,
        "闪卡概率": 0
    },
    {
        "Gacha根ID": 10002,
        "道具ID": 15404,
        "类型": 22,
        "概率权重": 100,
        "闪卡概率": 0
    },
    {
        "Gacha根ID": 10002,
        "道具ID": 11405,
        "类型": 22,
        "概率权重": 100,
        "闪卡概率": 0
    },
    {
        "Gacha根ID": 10002,
        "道具ID": 12405,
        "类型": 22,
        "概率权重": 100,
        "闪卡概率": 0
    },
    {
        "Gacha根ID": 10002,
        "道具ID": 14407,
        "类型": 22,
        "概率权重": 100,
        "闪卡概率": 0
    },
    {
        "Gacha根ID": 10002,
        "道具ID": 14408,
        "类型": 22,
        "概率权重": 100,
        "闪卡概率": 0
    },
    {
        "Gacha根ID": 10002,
        "道具ID": 15405,
        "类型": 22,
        "概率权重": 100,
        "闪卡概率": 0
    },
    {
        "Gacha根ID": 10002,
        "道具ID": 11301,
        "类型": 23,
        "概率权重": 100,
        "闪卡概率": 0
    },
    {
        "Gacha根ID": 10002,
        "道具ID": 11302,
        "类型": 23,
        "概率权重": 100,
        "闪卡概率": 0
    },
    {
        "Gacha根ID": 10002,
        "道具ID": 11306,
        "类型": 23,
        "概率权重": 100,
        "闪卡概率": 0
    },
    {
        "Gacha根ID": 10002,
        "道具ID": 12301,
        "类型": 23,
        "概率权重": 100,
        "闪卡概率": 0
    },
    {
        "Gacha根ID": 10002,
        "道具ID": 12302,
        "类型": 23,
        "概率权重": 100,
        "闪卡概率": 0
    },
    {
        "Gacha根ID": 10002,
        "道具ID": 12305,
        "类型": 23,
        "概率权重": 100,
        "闪卡概率": 0
    },
    {
        "Gacha根ID": 10002,
        "道具ID": 13303,
        "类型": 23,
        "概率权重": 100,
        "闪卡概率": 0
    },
    {
        "Gacha根ID": 10002,
        "道具ID": 14301,
        "类型": 23,
        "概率权重": 100,
        "闪卡概率": 0
    },
    {
        "Gacha根ID": 10002,
        "道具ID": 14302,
        "类型": 23,
        "概率权重": 100,
        "闪卡概率": 0
    },
    {
        "Gacha根ID": 10002,
        "道具ID": 14304,
        "类型": 23,
        "概率权重": 100,
        "闪卡概率": 0
    },
    {
        "Gacha根ID": 10002,
        "道具ID": 15301,
        "类型": 23,
        "概率权重": 100,
        "闪卡概率": 0
    },
    {
        "Gacha根ID": 10002,
        "道具ID": 15302,
        "类型": 23,
        "概率权重": 100,
        "闪卡概率": 0
    },
    {
        "Gacha根ID": 10002,
        "道具ID": 15304,
        "类型": 23,
        "概率权重": 100,
        "闪卡概率": 0
    },
    {
        "Gacha根ID": 10002,
        "道具ID": 11304,
        "类型": 23,
        "概率权重": 100,
        "闪卡概率": 0
    },
    {
        "Gacha根ID": 10002,
        "道具ID": 12304,
        "类型": 23,
        "概率权重": 100,
        "闪卡概率": 0
    },
    {
        "Gacha根ID": 10002,
        "道具ID": 14306,
        "类型": 23,
        "概率权重": 100,
        "闪卡概率": 0
    },
    {
        "Gacha根ID": 10002,
        "道具ID": 15306,
        "类型": 23,
        "概率权重": 100,
        "闪卡概率": 0
    },
    {
        "Gacha根ID": 10003,
        "道具ID": 1016,
        "类型": 11,
        "概率权重": 100,
        "闪卡概率": 0
    },
    {
        "Gacha根ID": 10003,
        "道具ID": 1003,
        "类型": 11,
        "概率权重": 100,
        "闪卡概率": 0
    },
    {
        "Gacha根ID": 10003,
        "道具ID": 1022,
        "类型": 11,
        "概率权重": "",
        "闪卡概率": 0
    },
    {
        "Gacha根ID": 10003,
        "道具ID": 1030,
        "类型": 11,
        "概率权重": "",
        "闪卡概率": 0
    },
    {
        "Gacha根ID": 10003,
        "道具ID": 1026,
        "类型": 11,
        "概率权重": "",
        "闪卡概率": 0
    },
    {
        "Gacha根ID": 10003,
        "道具ID": 1029,
        "类型": 11,
        "概率权重": "",
        "闪卡概率": 0
    },
    {
        "Gacha根ID": 10003,
        "道具ID": 1006,
        "类型": 12,
        "概率权重": 100,
        "闪卡概率": 0
    },
    {
        "Gacha根ID": 10003,
        "道具ID": 1014,
        "类型": 12,
        "概率权重": 100,
        "闪卡概率": 0
    },
    {
        "Gacha根ID": 10003,
        "道具ID": 1015,
        "类型": 12,
        "概率权重": 100,
        "闪卡概率": 0
    },
    {
        "Gacha根ID": 10003,
        "道具ID": 1020,
        "类型": 12,
        "概率权重": 100,
        "闪卡概率": 0
    },
    {
        "Gacha根ID": 10003,
        "道具ID": 1021,
        "类型": 12,
        "概率权重": 100,
        "闪卡概率": 0
    },
    {
        "Gacha根ID": 10003,
        "道具ID": 1023,
        "类型": 12,
        "概率权重": 100,
        "闪卡概率": 0
    },
    {
        "Gacha根ID": 10003,
        "道具ID": 1024,
        "类型": 12,
        "概率权重": 100,
        "闪卡概率": 0
    },
    {
        "Gacha根ID": 10003,
        "道具ID": 1025,
        "类型": 12,
        "概率权重": "",
        "闪卡概率": 0
    },
    {
        "Gacha根ID": 10003,
        "道具ID": 1027,
        "类型": 12,
        "概率权重": 100,
        "闪卡概率": 0
    },
    {
        "Gacha根ID": 10003,
        "道具ID": 1031,
        "类型": 12,
        "概率权重": "",
        "闪卡概率": 0
    },
    {
        "Gacha根ID": 10003,
        "道具ID": 1032,
        "类型": 12,
        "概率权重": 100,
        "闪卡概率": 0
    },
    {
        "Gacha根ID": 10003,
        "道具ID": 1034,
        "类型": 12,
        "概率权重": 100,
        "闪卡概率": 0
    },
    {
        "Gacha根ID": 10003,
        "道具ID": 11501,
        "类型": 21,
        "概率权重": 100,
        "闪卡概率": 0
    },
    {
        "Gacha根ID": 10003,
        "道具ID": 11502,
        "类型": 21,
        "概率权重": 100,
        "闪卡概率": 0
    },
    {
        "Gacha根ID": 10003,
        "道具ID": 12501,
        "类型": 21,
        "概率权重": 100,
        "闪卡概率": 0
    },
    {
        "Gacha根ID": 10003,
        "道具ID": 12502,
        "类型": 21,
        "概率权重": 100,
        "闪卡概率": 0
    },
    {
        "Gacha根ID": 10003,
        "道具ID": 13504,
        "类型": 21,
        "概率权重": 100,
        "闪卡概率": 0
    },
    {
        "Gacha根ID": 10003,
        "道具ID": 13505,
        "类型": 21,
        "概率权重": 100,
        "闪卡概率": 0
    },
    {
        "Gacha根ID": 10003,
        "道具ID": 14501,
        "类型": 21,
        "概率权重": 100,
        "闪卡概率": 0
    },
    {
        "Gacha根ID": 10003,
        "道具ID": 14502,
        "类型": 21,
        "概率权重": 100,
        "闪卡概率": 0
    },
    {
        "Gacha根ID": 10003,
        "道具ID": 15501,
        "类型": 21,
        "概率权重": 100,
        "闪卡概率": 0
    },
    {
        "Gacha根ID": 10003,
        "道具ID": 15502,
        "类型": 21,
        "概率权重": 100,
        "闪卡概率": 0
    },
    {
        "Gacha根ID": 10003,
        "道具ID": 11401,
        "类型": 22,
        "概率权重": 100,
        "闪卡概率": 0
    },
    {
        "Gacha根ID": 10003,
        "道具ID": 11402,
        "类型": 22,
        "概率权重": 100,
        "闪卡概率": 0
    },
    {
        "Gacha根ID": 10003,
        "道具ID": 11404,
        "类型": 22,
        "概率权重": 100,
        "闪卡概率": 0
    },
    {
        "Gacha根ID": 10003,
        "道具ID": 11407,
        "类型": 22,
        "概率权重": 100,
        "闪卡概率": 0
    },
    {
        "Gacha根ID": 10003,
        "道具ID": 12401,
        "类型": 22,
        "概率权重": 100,
        "闪卡概率": 0
    },
    {
        "Gacha根ID": 10003,
        "道具ID": 12402,
        "类型": 22,
        "概率权重": 100,
        "闪卡概率": 0
    },
    {
        "Gacha根ID": 10003,
        "道具ID": 12404,
        "类型": 22,
        "概率权重": 100,
        "闪卡概率": 0
    },
    {
        "Gacha根ID": 10003,
        "道具ID": 12406,
        "类型": 22,
        "概率权重": 100,
        "闪卡概率": 0
    },
    {
        "Gacha根ID": 10003,
        "道具ID": 13401,
        "类型": 22,
        "概率权重": 100,
        "闪卡概率": 0
    },
    {
        "Gacha根ID": 10003,
        "道具ID": 13404,
        "类型": 22,
        "概率权重": 100,
        "闪卡概率": 0
    },
    {
        "Gacha根ID": 10003,
        "道具ID": 14401,
        "类型": 22,
        "概率权重": 100,
        "闪卡概率": 0
    },
    {
        "Gacha根ID": 10003,
        "道具ID": 14402,
        "类型": 22,
        "概率权重": 100,
        "闪卡概率": 0
    },
    {
        "Gacha根ID": 10003,
        "道具ID": 14403,
        "类型": 22,
        "概率权重": 100,
        "闪卡概率": 0
    },
    {
        "Gacha根ID": 10003,
        "道具ID": 14404,
        "类型": 22,
        "概率权重": 100,
        "闪卡概率": 0
    },
    {
        "Gacha根ID": 10003,
        "道具ID": 15401,
        "类型": 22,
        "概率权重": 100,
        "闪卡概率": 0
    },
    {
        "Gacha根ID": 10003,
        "道具ID": 15402,
        "类型": 22,
        "概率权重": 100,
        "闪卡概率": 0
    },
    {
        "Gacha根ID": 10003,
        "道具ID": 15403,
        "类型": 22,
        "概率权重": 100,
        "闪卡概率": 0
    },
    {
        "Gacha根ID": 10003,
        "道具ID": 15404,
        "类型": 22,
        "概率权重": 100,
        "闪卡概率": 0
    },
    {
        "Gacha根ID": 10003,
        "道具ID": 11405,
        "类型": 22,
        "概率权重": 100,
        "闪卡概率": 0
    },
    {
        "Gacha根ID": 10003,
        "道具ID": 12405,
        "类型": 22,
        "概率权重": 100,
        "闪卡概率": 0
    },
    {
        "Gacha根ID": 10003,
        "道具ID": 14407,
        "类型": 22,
        "概率权重": 100,
        "闪卡概率": 0
    },
    {
        "Gacha根ID": 10003,
        "道具ID": 14408,
        "类型": 22,
        "概率权重": 100,
        "闪卡概率": 0
    },
    {
        "Gacha根ID": 10003,
        "道具ID": 15405,
        "类型": 22,
        "概率权重": 100,
        "闪卡概率": 0
    },
    {
        "Gacha根ID": 10003,
        "道具ID": 11301,
        "类型": 23,
        "概率权重": 100,
        "闪卡概率": 0
    },
    {
        "Gacha根ID": 10003,
        "道具ID": 11302,
        "类型": 23,
        "概率权重": 100,
        "闪卡概率": 0
    },
    {
        "Gacha根ID": 10003,
        "道具ID": 11306,
        "类型": 23,
        "概率权重": 100,
        "闪卡概率": 0
    },
    {
        "Gacha根ID": 10003,
        "道具ID": 12301,
        "类型": 23,
        "概率权重": 100,
        "闪卡概率": 0
    },
    {
        "Gacha根ID": 10003,
        "道具ID": 12302,
        "类型": 23,
        "概率权重": 100,
        "闪卡概率": 0
    },
    {
        "Gacha根ID": 10003,
        "道具ID": 12305,
        "类型": 23,
        "概率权重": 100,
        "闪卡概率": 0
    },
    {
        "Gacha根ID": 10003,
        "道具ID": 13303,
        "类型": 23,
        "概率权重": 100,
        "闪卡概率": 0
    },
    {
        "Gacha根ID": 10003,
        "道具ID": 14301,
        "类型": 23,
        "概率权重": 100,
        "闪卡概率": 0
    },
    {
        "Gacha根ID": 10003,
        "道具ID": 14302,
        "类型": 23,
        "概率权重": 100,
        "闪卡概率": 0
    },
    {
        "Gacha根ID": 10003,
        "道具ID": 14304,
        "类型": 23,
        "概率权重": 100,
        "闪卡概率": 0
    },
    {
        "Gacha根ID": 10003,
        "道具ID": 15301,
        "类型": 23,
        "概率权重": 100,
        "闪卡概率": 0
    },
    {
        "Gacha根ID": 10003,
        "道具ID": 15302,
        "类型": 23,
        "概率权重": 100,
        "闪卡概率": 0
    },
    {
        "Gacha根ID": 10003,
        "道具ID": 15304,
        "类型": 23,
        "概率权重": 100,
        "闪卡概率": 0
    },
    {
        "Gacha根ID": 10003,
        "道具ID": 11304,
        "类型": 23,
        "概率权重": 100,
        "闪卡概率": 0
    },
    {
        "Gacha根ID": 10003,
        "道具ID": 12304,
        "类型": 23,
        "概率权重": 100,
        "闪卡概率": 0
    },
    {
        "Gacha根ID": 10003,
        "道具ID": 14306,
        "类型": 23,
        "概率权重": 100,
        "闪卡概率": 0
    },
    {
        "Gacha根ID": 10003,
        "道具ID": 15306,
        "类型": 23,
        "概率权重": 100,
        "闪卡概率": 0
    },
    {
        "Gacha根ID": 20001,
        "道具ID": 1016,
        "类型": 11,
        "概率权重": 100,
        "闪卡概率": 0
    },
    {
        "Gacha根ID": 20001,
        "道具ID": 1003,
        "类型": 11,
        "概率权重": 100,
        "闪卡概率": 0
    },
    {
        "Gacha根ID": 20001,
        "道具ID": 1014,
        "类型": 12,
        "概率权重": 100,
        "闪卡概率": 0
    },
    {
        "Gacha根ID": 20001,
        "道具ID": 1020,
        "类型": 12,
        "概率权重": 100,
        "闪卡概率": 0
    },
    {
        "Gacha根ID": 20001,
        "道具ID": 1023,
        "类型": 12,
        "概率权重": 100,
        "闪卡概率": 0
    },
    {
        "Gacha根ID": 20001,
        "道具ID": 1024,
        "类型": 12,
        "概率权重": 100,
        "闪卡概率": 0
    },
    {
        "Gacha根ID": 20001,
        "道具ID": 1027,
        "类型": 12,
        "概率权重": 100,
        "闪卡概率": 0
    },
    {
        "Gacha根ID": 20001,
        "道具ID": 1032,
        "类型": 12,
        "概率权重": 100,
        "闪卡概率": 0
    },
    {
        "Gacha根ID": 20001,
        "道具ID": 1034,
        "类型": 12,
        "概率权重": 100,
        "闪卡概率": 0
    },
    {
        "Gacha根ID": 20001,
        "道具ID": 11501,
        "类型": 21,
        "概率权重": 100,
        "闪卡概率": 0
    },
    {
        "Gacha根ID": 20001,
        "道具ID": 11502,
        "类型": 21,
        "概率权重": 100,
        "闪卡概率": 0
    },
    {
        "Gacha根ID": 20001,
        "道具ID": 12501,
        "类型": 21,
        "概率权重": 100,
        "闪卡概率": 0
    },
    {
        "Gacha根ID": 20001,
        "道具ID": 12502,
        "类型": 21,
        "概率权重": 100,
        "闪卡概率": 0
    },
    {
        "Gacha根ID": 20001,
        "道具ID": 13504,
        "类型": 21,
        "概率权重": 100,
        "闪卡概率": 0
    },
    {
        "Gacha根ID": 20001,
        "道具ID": 13505,
        "类型": 21,
        "概率权重": 100,
        "闪卡概率": 0
    },
    {
        "Gacha根ID": 20001,
        "道具ID": 14501,
        "类型": 21,
        "概率权重": 100,
        "闪卡概率": 0
    },
    {
        "Gacha根ID": 20001,
        "道具ID": 14502,
        "类型": 21,
        "概率权重": 100,
        "闪卡概率": 0
    },
    {
        "Gacha根ID": 20001,
        "道具ID": 15501,
        "类型": 21,
        "概率权重": 100,
        "闪卡概率": 0
    },
    {
        "Gacha根ID": 20001,
        "道具ID": 15502,
        "类型": 21,
        "概率权重": 100,
        "闪卡概率": 0
    },
    {
        "Gacha根ID": 20001,
        "道具ID": 11401,
        "类型": 22,
        "概率权重": 100,
        "闪卡概率": 0
    },
    {
        "Gacha根ID": 20001,
        "道具ID": 11402,
        "类型": 22,
        "概率权重": 100,
        "闪卡概率": 0
    },
    {
        "Gacha根ID": 20001,
        "道具ID": 11404,
        "类型": 22,
        "概率权重": 100,
        "闪卡概率": 0
    },
    {
        "Gacha根ID": 20001,
        "道具ID": 11407,
        "类型": 22,
        "概率权重": 100,
        "闪卡概率": 0
    },
    {
        "Gacha根ID": 20001,
        "道具ID": 12401,
        "类型": 22,
        "概率权重": 100,
        "闪卡概率": 0
    },
    {
        "Gacha根ID": 20001,
        "道具ID": 12402,
        "类型": 22,
        "概率权重": 100,
        "闪卡概率": 0
    },
    {
        "Gacha根ID": 20001,
        "道具ID": 12404,
        "类型": 22,
        "概率权重": 100,
        "闪卡概率": 0
    },
    {
        "Gacha根ID": 20001,
        "道具ID": 12406,
        "类型": 22,
        "概率权重": 100,
        "闪卡概率": 0
    },
    {
        "Gacha根ID": 20001,
        "道具ID": 13401,
        "类型": 22,
        "概率权重": 100,
        "闪卡概率": 0
    },
    {
        "Gacha根ID": 20001,
        "道具ID": 13404,
        "类型": 22,
        "概率权重": 100,
        "闪卡概率": 0
    },
    {
        "Gacha根ID": 20001,
        "道具ID": 14401,
        "类型": 22,
        "概率权重": 100,
        "闪卡概率": 0
    },
    {
        "Gacha根ID": 20001,
        "道具ID": 14402,
        "类型": 22,
        "概率权重": 100,
        "闪卡概率": 0
    },
    {
        "Gacha根ID": 20001,
        "道具ID": 14403,
        "类型": 22,
        "概率权重": 100,
        "闪卡概率": 0
    },
    {
        "Gacha根ID": 20001,
        "道具ID": 14404,
        "类型": 22,
        "概率权重": 100,
        "闪卡概率": 0
    },
    {
        "Gacha根ID": 20001,
        "道具ID": 15401,
        "类型": 22,
        "概率权重": 100,
        "闪卡概率": 0
    },
    {
        "Gacha根ID": 20001,
        "道具ID": 15402,
        "类型": 22,
        "概率权重": 100,
        "闪卡概率": 0
    },
    {
        "Gacha根ID": 20001,
        "道具ID": 15403,
        "类型": 22,
        "概率权重": 100,
        "闪卡概率": 0
    },
    {
        "Gacha根ID": 20001,
        "道具ID": 15404,
        "类型": 22,
        "概率权重": 100,
        "闪卡概率": 0
    },
    {
        "Gacha根ID": 20001,
        "道具ID": 11405,
        "类型": 22,
        "概率权重": 100,
        "闪卡概率": 0
    },
    {
        "Gacha根ID": 20001,
        "道具ID": 12405,
        "类型": 22,
        "概率权重": 100,
        "闪卡概率": 0
    },
    {
        "Gacha根ID": 20001,
        "道具ID": 14407,
        "类型": 22,
        "概率权重": 100,
        "闪卡概率": 0
    },
    {
        "Gacha根ID": 20001,
        "道具ID": 14408,
        "类型": 22,
        "概率权重": 100,
        "闪卡概率": 0
    },
    {
        "Gacha根ID": 20001,
        "道具ID": 15405,
        "类型": 22,
        "概率权重": 100,
        "闪卡概率": 0
    },
    {
        "Gacha根ID": 20001,
        "道具ID": 11301,
        "类型": 23,
        "概率权重": 100,
        "闪卡概率": 0
    },
    {
        "Gacha根ID": 20001,
        "道具ID": 11302,
        "类型": 23,
        "概率权重": 100,
        "闪卡概率": 0
    },
    {
        "Gacha根ID": 20001,
        "道具ID": 11306,
        "类型": 23,
        "概率权重": 100,
        "闪卡概率": 0
    },
    {
        "Gacha根ID": 20001,
        "道具ID": 12301,
        "类型": 23,
        "概率权重": 100,
        "闪卡概率": 0
    },
    {
        "Gacha根ID": 20001,
        "道具ID": 12302,
        "类型": 23,
        "概率权重": 100,
        "闪卡概率": 0
    },
    {
        "Gacha根ID": 20001,
        "道具ID": 12305,
        "类型": 23,
        "概率权重": 100,
        "闪卡概率": 0
    },
    {
        "Gacha根ID": 20001,
        "道具ID": 13303,
        "类型": 23,
        "概率权重": 100,
        "闪卡概率": 0
    },
    {
        "Gacha根ID": 20001,
        "道具ID": 14301,
        "类型": 23,
        "概率权重": 100,
        "闪卡概率": 0
    },
    {
        "Gacha根ID": 20001,
        "道具ID": 14302,
        "类型": 23,
        "概率权重": 100,
        "闪卡概率": 0
    },
    {
        "Gacha根ID": 20001,
        "道具ID": 14304,
        "类型": 23,
        "概率权重": 100,
        "闪卡概率": 0
    },
    {
        "Gacha根ID": 20001,
        "道具ID": 15301,
        "类型": 23,
        "概率权重": 100,
        "闪卡概率": 0
    },
    {
        "Gacha根ID": 20001,
        "道具ID": 15302,
        "类型": 23,
        "概率权重": 100,
        "闪卡概率": 0
    },
    {
        "Gacha根ID": 20001,
        "道具ID": 15304,
        "类型": 23,
        "概率权重": 100,
        "闪卡概率": 0
    },
    {
        "Gacha根ID": 20001,
        "道具ID": 11304,
        "类型": 23,
        "概率权重": 100,
        "闪卡概率": 0
    },
    {
        "Gacha根ID": 20001,
        "道具ID": 12304,
        "类型": 23,
        "概率权重": 100,
        "闪卡概率": 0
    },
    {
        "Gacha根ID": 20001,
        "道具ID": 14306,
        "类型": 23,
        "概率权重": 100,
        "闪卡概率": 0
    },
    {
        "Gacha根ID": 20001,
        "道具ID": 15306,
        "类型": 23,
        "概率权重": 100,
        "闪卡概率": 0
    }
]