[
    {
        "Id": "11001",
        "abilityStates": [
            "65536",
            "16",
            "32",
            "128",
            "2048",
            "16777216",
            "32768",
            "8388608",
            "4194304",
            "33554432"
        ]
    },
    {
        "Id": "11002",
        "abilityStates": [
            "65536",
            "16",
            "32",
            "128",
            "2048",
            "4096",
            "32768",
            "1048576",
            "2097152",
            "0"
        ]
    },
    {
        "Id": "11003",
        "abilityStates": [
            "65536",
            "128",
            "4096",
            "256",
            "1048576",
            "134217728",
            "32768",
            "0",
            "0",
            "0"
        ]
    },
    {
        "Id": "12001",
        "abilityStates": [
            "65536",
            "16",
            "32",
            "128",
            "2048",
            "0",
            "0",
            "0",
            "0",
            "0"
        ]
    },
    {
        "Id": "12002",
        "abilityStates": [
            "16777216",
            "32768",
            "8388608",
            "4194304",
            "33554432",
            "0",
            "0",
            "0",
            "0",
            "0"
        ]
    },
    {
        "Id": "13001",
        "abilityStates": [
            "65536",
            "32768",
            "0",
            "0",
            "0",
            "0",
            "0",
            "0",
            "0",
            "0"
        ]
    },
    {
        "Id": "13002",
        "abilityStates": [
            "65536",
            "4096",
            "0",
            "0",
            "0",
            "0",
            "0",
            "0",
            "0",
            "0"
        ]
    },
    {
        "Id": "14001",
        "abilityStates": [
            "4096",
            "0",
            "0",
            "0",
            "0",
            "0",
            "0",
            "0",
            "0",
            "0"
        ]
    },
    {
        "Id": "14002",
        "abilityStates": [
            "65536",
            "0",
            "0",
            "0",
            "0",
            "0",
            "0",
            "0",
            "0",
            "0"
        ]
    },
    {
        "Id": "14003",
        "abilityStates": [
            "16384",
            "0",
            "0",
            "0",
            "0",
            "0",
            "0",
            "0",
            "0",
            "0"
        ]
    },
    {
        "Id": "14004",
        "abilityStates": [
            "2048",
            "0",
            "0",
            "0",
            "0",
            "0",
            "0",
            "0",
            "0",
            "0"
        ]
    }
]